esp_idf_nvs_partition_gen/__init__.py
esp_idf_nvs_partition_gen/__main__.py
esp_idf_nvs_partition_gen/nvs_partition_gen.py
esp_idf_nvs_partition_gen-0.2.0.dist-info/LICENSE
esp_idf_nvs_partition_gen-0.2.0.dist-info/METADATA
esp_idf_nvs_partition_gen-0.2.0.dist-info/WHEEL
esp_idf_nvs_partition_gen-0.2.0.dist-info/top_level.txt
esp_idf_nvs_partition_gen-0.2.0.dist-info/RECORD
