Metadata-Version: 2.1
Name: esp_idf_nvs_partition_gen
Version: 0.2.0
Summary: ESP-IDF NVS partition generation tool
Author: Espressif Systems
License:                                  Apache License
Project-URL: Homepage, https://github.com/espressif/esp-idf-nvs-partition-gen
Keywords: espressif,esp-idf,nvs,nvs-partition-gen
Classifier: Development Status :: 4 - Beta
Classifier: Intended Audience :: Developers
Classifier: Natural Language :: English
Classifier: Environment :: Console
Classifier: Topic :: Software Development :: Embedded Systems
Classifier: License :: OSI Approved :: Apache Software License
Classifier: Programming Language :: Python :: 3.8
Classifier: Programming Language :: Python :: 3.9
Classifier: Programming Language :: Python :: 3.10
Classifier: Programming Language :: Python :: 3.11
Classifier: Programming Language :: Python :: 3.12
Classifier: Operating System :: POSIX
Classifier: Operating System :: Microsoft :: Windows
Classifier: Operating System :: MacOS :: MacOS X
Requires-Python: >=3.8
License-File: LICENSE
Requires-Dist: cryptography
Provides-Extra: dev
Requires-Dist: pre-commit; extra == "dev"
